VHDL/Simulations/alu/alu8.vhd
library IEEE;
use IEEE.STD_LOGIC_1164.ALL;
use IEEE.NUMERIC_STD.ALL;

entity alu8 is
    Port (
        A      : in  STD_LOGIC_VECTOR(7 downto 0);
        B      : in  STD_LOGIC_VECTOR(7 downto 0);
        Cin    : in  STD_LOGIC := '0';
        -- Operation selects
        ADD    : in  STD_LOGIC;
        SUB    : in  STD_LOGIC;
        SHL    : in  STD_LOGIC;
        SHR    : in  STD_LOGIC;
        XOR_OP : in  STD_LOGIC;
        OR_OP  : in  STD_LOGIC;
        AND_OP : in  STD_LOGIC;
        NOT_OP : in  STD_LOGIC;
        -- Outputs
        RESULT : out STD_LOGIC_VECTOR(7 downto 0);
        Z      : out STD_LOGIC;  -- Zero flag
        N      : out STD_LOGIC;  -- Negative flag
        C      : out STD_LOGIC;  -- Carry flag
        V      : out STD_LOGIC;  -- Overflow flag
        H      : out STD_LOGIC   -- Half-carry (bit 3 to 4)
    );
end alu8;

architecture Behavioral of alu8 is
    signal A_unsigned, B_unsigned : UNSIGNED(7 downto 0);
    signal temp_result : UNSIGNED(8 downto 0); -- 9-bit for carry
    signal res8 : STD_LOGIC_VECTOR(7 downto 0);
begin
    A_unsigned <= UNSIGNED(A);
    B_unsigned <= UNSIGNED(B);

    process(A_unsigned, B_unsigned, Cin, ADD, SUB, SHL, SHR, XOR_OP, OR_OP, AND_OP, NOT_OP)
        variable Cin_int : integer;
    begin
        -- Convert Cin to integer
        if Cin = '0' then
            Cin_int := 0;
        else
            Cin_int := 1;
        end if;

        -- Defaults
        temp_result <= (others => '0');
        res8 <= (others => '0');
        C <= '0';
        V <= '0';
        H <= '0';

        -- ADD
        if ADD = '1' then
            temp_result <= ('0' & A_unsigned) + ('0' & B_unsigned);
            if Cin_int = 1 then
                temp_result <= temp_result + 1;
            end if;
            res8 <= STD_LOGIC_VECTOR(temp_result(7 downto 0));
            C <= temp_result(8);

            -- Half-carry: sum of lower nibble > 15
            if (to_integer(A_unsigned(3 downto 0)) + to_integer(B_unsigned(3 downto 0)) + Cin_int) > 15 then
                H <= '1';
            else
                H <= '0';
            end if;

            -- Overflow: signed addition
            if (A_unsigned(7) = B_unsigned(7)) and (res8(7) /= A_unsigned(7)) then
                V <= '1';
            else
                V <= '0';
            end if;

        -- SUB
        elsif SUB = '1' then
            temp_result <= ('0' & A_unsigned) + ('0' & (not B_unsigned));
            if Cin_int = 0 then
                temp_result <= temp_result + 1;
            end if;
            res8 <= STD_LOGIC_VECTOR(temp_result(7 downto 0));
            C <= temp_result(8);

            -- Half-carry for subtraction
            if (to_integer(A_unsigned(3 downto 0)) < to_integer(B_unsigned(3 downto 0)) + Cin_int) then
                H <= '1';
            else
                H <= '0';
            end if;

            -- Overflow: signed subtraction
            if (A_unsigned(7) /= B_unsigned(7)) and (res8(7) /= A_unsigned(7)) then
                V <= '1';
            else
                V <= '0';
            end if;

        -- SHL
        elsif SHL = '1' then
            res8 <= STD_LOGIC_VECTOR(A_unsigned(6 downto 0) & '0');
            C <= A_unsigned(7);

        -- SHR
        elsif SHR = '1' then
            res8 <= STD_LOGIC_VECTOR('0' & A_unsigned(7 downto 1));
            C <= A_unsigned(0);

        -- XOR
        elsif XOR_OP = '1' then
            res8 <= STD_LOGIC_VECTOR(A_unsigned xor B_unsigned);

        -- OR
        elsif OR_OP = '1' then
            res8 <= STD_LOGIC_VECTOR(A_unsigned or B_unsigned);

        -- AND
        elsif AND_OP = '1' then
            res8 <= STD_LOGIC_VECTOR(A_unsigned and B_unsigned);

        -- NOT
        elsif NOT_OP = '1' then
            res8 <= STD_LOGIC_VECTOR(not A_unsigned);

        else
            res8 <= (others => '0');
        end if;

        -- Flags
        if res8 = "00000000" then
            Z <= '1';
        else
            Z <= '0';
        end if;

        N <= res8(7);

    end process;

    RESULT <= res8;

end Behavioral;

VHDL/RATZAM-CPU/src/cpu8.vhd
library IEEE;
use IEEE.STD_LOGIC_1164.ALL;
use IEEE.NUMERIC_STD.ALL;

entity cpu8 is
    port(
        clk     : in  std_logic;
        rst     : in  std_logic;
        -- Memory interface
        mem_addr     : out std_logic_vector(7 downto 0);
        mem_data_in  : in  std_logic_vector(7 downto 0);
        mem_data_out : out std_logic_vector(7 downto 0);
        mem_we       : out std_logic;
        mem_re       : out std_logic;
        -- I/O interface
        io_data_in   : in  std_logic_vector(7 downto 0);
        io_data_out  : out std_logic_vector(7 downto 0);
        io_we        : out std_logic;
        io_re        : out std_logic;
        -- Interrupt input
        interrupt    : in  std_logic
    );
end entity;

architecture rtl of cpu8 is

    -- CPU registers
    signal PC          : std_logic_vector(7 downto 0) := (others=>'0');
    signal CIR_opcode  : std_logic_vector(7 downto 0) := (others=>'0');
    signal TMP_operand : std_logic_vector(7 downto 0) := (others=>'0');
    signal ACC         : std_logic_vector(7 downto 0) := (others=>'0');
    signal SP          : std_logic_vector(7 downto 0) := x"FF";
    signal HP          : std_logic_vector(7 downto 0) := x"00";
    signal STATUS      : std_logic_vector(4 downto 0) := (others=>'0'); -- Z,N,C,V,I
    signal TMP_data    : std_logic_vector(7 downto 0) := (others=>'0');

    -- Memory interface signals
    signal mem_addr_r     : std_logic_vector(7 downto 0);
    signal mem_data_out_r : std_logic_vector(7 downto 0);
    signal mem_we_r       : std_logic := '0';
    signal mem_re_r       : std_logic := '0';

    -- I/O interface internal signals
    signal io_data_out_r  : std_logic_vector(7 downto 0);
    signal io_we_r        : std_logic := '0';
    signal io_re_r        : std_logic := '0';

    -- ALU control signals
    signal alu_A, alu_B   : std_logic_vector(7 downto 0);
    signal alu_RESULT     : std_logic_vector(7 downto 0);
    signal alu_C, alu_Z, alu_N, alu_V, alu_H : std_logic;
    signal alu_ADD, alu_SUB, alu_SHL, alu_SHR, alu_XOR, alu_OR, alu_AND, alu_NOT : std_logic;

    -- CPU FSM states (INTERRUPT renamed to INT_STATE)
    type state_type is (FETCH_OP, FETCH_OPERAND, EXECUTE, MEMORY_ACCESS, WRITEBACK, INT_STATE);
    signal state : state_type := FETCH_OP;

begin

    ----------------------------------------------------------------------
    -- ALU instance
    ----------------------------------------------------------------------
    alu_inst : entity work.alu8
        port map(
            A      => alu_A,
            B      => alu_B,
            Cin    => '0',
            ADD    => alu_ADD,
            SUB    => alu_SUB,
            SHL    => alu_SHL,
            SHR    => alu_SHR,
            XOR_OP => alu_XOR,
            OR_OP  => alu_OR,
            AND_OP => alu_AND,
            NOT_OP => alu_NOT,
            RESULT => alu_RESULT,
            Z      => alu_Z,
            N      => alu_N,
            C      => alu_C,
            V      => alu_V,
            H      => alu_H
        );

    ----------------------------------------------------------------------
    -- CPU main process
    ----------------------------------------------------------------------
    process(clk,rst)
    begin
        if rst='1' then
            PC <= (others=>'0');
            ACC <= (others=>'0');
            SP <= x"FF";
            HP <= x"00";
            STATUS <= (others=>'0');
            TMP_operand <= (others=>'0');
            TMP_data <= (others=>'0');
            CIR_opcode <= (others=>'0');
            state <= FETCH_OP;

            mem_we_r <= '0';
            mem_re_r <= '0';
            io_we_r <= '0';
            io_re_r <= '0';

            -- Clear ALU signals
            alu_ADD <= '0'; alu_SUB <= '0'; alu_SHL <= '0'; alu_SHR <= '0';
            alu_XOR <= '0'; alu_OR <= '0'; alu_AND <= '0'; alu_NOT <= '0';

        elsif rising_edge(clk) then

            -- Interrupt detection
            if STATUS(0)='1' and interrupt='1' then
                state <= INT_STATE;
            end if;

            case state is

                when FETCH_OP =>
                    mem_addr_r <= PC;
                    mem_re_r <= '1';
                    state <= FETCH_OPERAND;

                when FETCH_OPERAND =>
                    CIR_opcode <= mem_data_in;
                    PC <= std_logic_vector(unsigned(PC)+1);
                    mem_addr_r <= PC;
                    mem_re_r <= '1';
                    state <= EXECUTE;

                when EXECUTE =>
                    TMP_operand <= mem_data_in;
                    mem_re_r <= '0';

                    -- Clear ALU signals
                    alu_ADD <= '0'; alu_SUB <= '0'; alu_SHL <= '0'; alu_SHR <= '0';
                    alu_XOR <= '0'; alu_OR <= '0'; alu_AND <= '0'; alu_NOT <= '0';
                    alu_A <= ACC;
                    alu_B <= TMP_operand;

                    case CIR_opcode is
                        when x"01" =>  -- LD addr
                            mem_addr_r <= TMP_operand;
                            mem_re_r <= '1';
                            state <= MEMORY_ACCESS;

                        when x"02" =>  -- JZ addr
                            if STATUS(4)='1' then -- Zero flag
                                PC <= TMP_operand;
                            end if;
                            state <= FETCH_OP;

                        when x"10" =>  -- PUSH ACC
                            mem_addr_r <= SP;
                            mem_data_out_r <= ACC;
                            mem_we_r <= '1';
                            SP <= std_logic_vector(unsigned(SP)-1);
                            state <= FETCH_OP;

                        when x"11" =>  -- POP ACC
                            SP <= std_logic_vector(unsigned(SP)+1);
                            mem_addr_r <= SP;
                            mem_re_r <= '1';
                            state <= MEMORY_ACCESS;

                        -- ALU instructions
                        when x"20" =>  -- ADD
                            alu_ADD <= '1';
                            state <= WRITEBACK;

                        when x"21" =>  -- SUB
                            alu_SUB <= '1';
                            state <= WRITEBACK;

                        when x"22" =>  -- AND
                            alu_AND <= '1';
                            state <= WRITEBACK;

                        when x"23" =>  -- OR
                            alu_OR <= '1';
                            state <= WRITEBACK;

                        when x"24" =>  -- XOR
                            alu_XOR <= '1';
                            state <= WRITEBACK;

                        when x"25" =>  -- NOT
                            alu_NOT <= '1';
                            state <= WRITEBACK;

                        when others =>
                            state <= FETCH_OP;
                    end case;

                when MEMORY_ACCESS =>
                    TMP_data <= mem_data_in;
                    ACC <= TMP_data;
                    mem_re_r <= '0';
                    mem_we_r <= '0';
                    state <= FETCH_OP;

                when WRITEBACK =>
                    ACC <= alu_RESULT;
                    -- Update CPU STATUS flags from ALU
                    STATUS(4) <= STATUS(4); -- interrupt enable unchanged
                    STATUS(3) <= alu_V;
                    STATUS(2) <= alu_C;
                    STATUS(1) <= alu_N;
                    STATUS(0) <= alu_Z;
                    state <= FETCH_OP;

                when INT_STATE =>
                    -- Push PC to stack, disable interrupt
                    mem_addr_r <= SP;
                    mem_data_out_r <= PC;
                    mem_we_r <= '1';
                    SP <= std_logic_vector(unsigned(SP)-1);
                    PC <= x"F2"; -- ISR address
                    STATUS(0) <= '0'; -- disable interrupts
                    state <= FETCH_OP;

                when others =>
                    state <= FETCH_OP;
            end case;

        end if;
    end process;

    ----------------------------------------------------------------------
    -- Output assignments
    ----------------------------------------------------------------------
    mem_addr <= mem_addr_r;
    mem_data_out <= mem_data_out_r;
    mem_we <= mem_we_r;
    mem_re <= mem_re_r;

    io_data_out <= io_data_out_r;
    io_we <= io_we_r;
    io_re <= io_re_r;

end architecture;

VHDL/RATZAM-CPU/tb/tb_cpu8.vhd
library IEEE;
use IEEE.STD_LOGIC_1164.ALL;
use IEEE.NUMERIC_STD.ALL;

entity tb_cpu8 is
end tb_cpu8;

architecture sim of tb_cpu8 is

    -- Clock & reset
    signal clk, rst : std_logic := '0';

    -- CPU <-> Memory signals
    signal mem_addr     : std_logic_vector(7 downto 0);
    signal mem_data_in  : std_logic_vector(7 downto 0);
    signal mem_data_out : std_logic_vector(7 downto 0);
    signal mem_we       : std_logic;
    signal mem_re       : std_logic;

    -- CPU <-> I/O
    signal io_data_in  : std_logic_vector(7 downto 0) := (others=>'0');
    signal io_data_out : std_logic_vector(7 downto 0);
    signal io_we       : std_logic;
    signal io_re       : std_logic;

    -- Interrupt
    signal interrupt : std_logic := '0';

    -- Simple 256-byte memory
    type ram_type is array (0 to 255) of std_logic_vector(7 downto 0);
    signal RAM : ram_type := (others => (others=>'0'));

begin

    -- Clock generation: 10 ns period
    clk <= not clk after 5 ns;

    -- Instantiate CPU
    DUT: entity work.cpu8
        port map(
            clk          => clk,
            rst          => rst,
            mem_addr     => mem_addr,
            mem_data_in  => mem_data_in,
            mem_data_out => mem_data_out,
            mem_we       => mem_we,
            mem_re       => mem_re,
            io_data_in   => io_data_in,
            io_data_out  => io_data_out,
            io_we        => io_we,
            io_re        => io_re,
            interrupt    => interrupt
        );

    -- Memory model process
    process(clk)
    begin
        if rising_edge(clk) then
            if mem_we='1' then
                RAM(to_integer(unsigned(mem_addr))) <= mem_data_out;
            end if;

            if mem_re='1' then
                mem_data_in <= RAM(to_integer(unsigned(mem_addr)));
            else
                mem_data_in <= (others=>'0');
            end if;
        end if;
    end process;

    -- Test sequence
    process
    begin
        -- Reset
        rst <= '1';
        wait for 20 ns;
        rst <= '0';
        wait for 20 ns;

        -- Load a small program into RAM
        -- Example: LD 0x10, ADD 0x11, PUSH ACC, POP ACC, JZ 0x20, I/O output
        RAM(0)  <= x"01"; RAM(1)  <= x"10"; -- LD 0x10
        RAM(2)  <= x"20"; RAM(3)  <= x"11"; -- ADD 0x11
        RAM(4)  <= x"10";                 -- PUSH ACC
        RAM(5)  <= x"11";                 -- POP ACC
        RAM(6)  <= x"02"; RAM(7)  <= x"20"; -- JZ 0x20
        RAM(8)  <= x"F0";                 -- I/O output

        -- Initialize data
        RAM(16) <= x"05"; -- operand 0x10
        RAM(17) <= x"03"; -- operand 0x11

        -- Let CPU run for a while
        wait for 500 ns;

        -- Trigger interrupt
        interrupt <= '1';
        wait for 20 ns;
        interrupt <= '0';

        wait for 200 ns;

        -- Finish simulation
        wait;
    end process;

end architecture;

VHDL/RATZAM-CPU/sim/wave.vcd
$date
  Wed Sep 17 11:53:35 2025
$end
$version
  GHDL v0
$end
$timescale
  1 fs
$end
$scope module standard $end
$upscope $end
$scope module std_logic_1164 $end
$upscope $end
$scope module numeric_std $end
$upscope $end
$scope module tb_cpu8 $end
$var reg 1 ! clk $end
$var reg 1 " rst $end
$var reg 8 # mem_addr[7:0] $end
$var reg 8 $ mem_data_in[7:0] $end
$var reg 8 % mem_data_out[7:0] $end
$var reg 1 & mem_we $end
$var reg 1 ' mem_re $end
$var reg 8 ( io_data_in[7:0] $end
$var reg 8 ) io_data_out[7:0] $end
$var reg 1 * io_we $end
$var reg 1 + io_re $end
$var reg 1 , interrupt $end
$comment ram is not handled $end
$scope module dut $end
$var reg 1 - clk $end
$var reg 1 . rst $end
$var reg 8 / mem_addr[7:0] $end
$var reg 8 0 mem_data_in[7:0] $end
$var reg 8 1 mem_data_out[7:0] $end
$var reg 1 2 mem_we $end
$var reg 1 3 mem_re $end
$var reg 8 4 io_data_in[7:0] $end
$var reg 8 5 io_data_out[7:0] $end
$var reg 1 6 io_we $end
$var reg 1 7 io_re $end
$var reg 1 8 interrupt $end
$var reg 8 9 pc[7:0] $end
$var reg 8 : cir_opcode[7:0] $end
$var reg 8 ; tmp_operand[7:0] $end
$var reg 8 < acc[7:0] $end
$var reg 8 = sp[7:0] $end
$var reg 8 > hp[7:0] $end
$var reg 5 ? status[4:0] $end
$var reg 8 @ tmp_data[7:0] $end
$var reg 8 A mem_addr_r[7:0] $end
$var reg 8 B mem_data_out_r[7:0] $end
$var reg 1 C mem_we_r $end
$var reg 1 D mem_re_r $end
$var reg 8 E io_data_out_r[7:0] $end
$var reg 1 F io_we_r $end
$var reg 1 G io_re_r $end
$var reg 8 H alu_a[7:0] $end
$var reg 8 I alu_b[7:0] $end
$var reg 8 J alu_result[7:0] $end
$var reg 1 K alu_c $end
$var reg 1 L alu_z $end
$var reg 1 M alu_n $end
$var reg 1 N alu_v $end
$var reg 1 O alu_h $end
$var reg 1 P alu_add $end
$var reg 1 Q alu_sub $end
$var reg 1 R alu_shl $end
$var reg 1 S alu_shr $end
$var reg 1 T alu_xor $end
$var reg 1 U alu_or $end
$var reg 1 V alu_and $end
$var reg 1 W alu_not $end
$comment state is not handled $end
$scope module alu_inst $end
$var reg 8 X a[7:0] $end
$var reg 8 Y b[7:0] $end
$var reg 1 Z cin $end
$var reg 1 [ add $end
$var reg 1 \ sub $end
$var reg 1 ] shl $end
$var reg 1 ^ shr $end
$var reg 1 _ xor_op $end
$var reg 1 ` or_op $end
$var reg 1 a and_op $end
$var reg 1 b not_op $end
$var reg 8 c result[7:0] $end
$var reg 1 d z $end
$var reg 1 e n $end
$var reg 1 f c $end
$var reg 1 g v $end
$var reg 1 h h $end
$var reg 8 i a_unsigned[7:0] $end
$var reg 8 j b_unsigned[7:0] $end
$var reg 9 k temp_result[8:0] $end
$var reg 8 l res8[7:0] $end
$upscope $end
$upscope $end
$upscope $end
$enddefinitions $end
#0
0!
1"
bUUUUUUUU #
bUUUUUUUU $
bUUUUUUUU %
0&
0'
b00000000 (
bUUUUUUUU )
0*
0+
0,
0-
1.
bUUUUUUUU /
bUUUUUUUU 0
bUUUUUUUU 1
02
03
b00000000 4
bUUUUUUUU 5
06
07
08
b00000000 9
b00000000 :
b00000000 ;
b00000000 <
b11111111 =
b00000000 >
b00000 ?
b00000000 @
bUUUUUUUU A
bUUUUUUUU B
0C
0D
bUUUUUUUU E
0F
0G
bUUUUUUUU H
bUUUUUUUU I
b00000000 J
0K
1L
0M
0N
0O
0P
0Q
0R
0S
0T
0U
0V
0W
bUUUUUUUU X
bUUUUUUUU Y
0Z
0[
0\
0]
0^
0_
0`
0a
0b
b00000000 c
1d
0e
0f
0g
0h
bUUUUUUUU i
bUUUUUUUU j
b000000000 k
b00000000 l
#5000000
1!
b00000000 $
1-
b00000000 0
#10000000
0!
0-
#15000000
1!
1-
#20000000
0!
0"
0-
0.
#25000000
1!
b00000000 #
1'
1-
b00000000 /
13
b00000000 A
1D
#30000000
0!
0-
#35000000
1!
1-
b00000001 9
#40000000
0!
0-
#45000000
1!
b0000000X $
0'
1-
b0000000X 0
03
0D
b00000000 H
b00000000 I
b00000000 X
b00000000 Y
b00000000 i
b00000000 j
#50000000
0!
0-
#55000000
1!
b00000001 #
b00000000 $
1'
1-
b00000001 /
b00000000 0
13
b00000001 A
1D
#60000000
0!
0-
#65000000
1!
b000X0000 $
1-
b000X0000 0
b00000010 9
#70000000
0!
0-
#75000000
1!
0'
1-
03
b000X0000 ;
0D
#80000000
0!
0-
#85000000
1!
b00000010 #
b00000000 $
1'
1-
b00000010 /
b00000000 0
13
b00000010 A
1D
#90000000
0!
0-
#95000000
1!
b00X00000 $
1-
b00X00000 0
b00000011 9
#100000000
0!
0-
#105000000
1!
0'
1-
03
b00X00000 ;
0D
b000X0000 I
b000X0000 Y
b000X0000 j
#110000000
0!
0-
#115000000
1!
b00000011 #
b00000000 $
1'
1-
b00000011 /
b00000000 0
13
b00000011 A
1D
#120000000
0!
0-
#125000000
1!
b000X000X $
1-
b000X000X 0
b00000100 9
#130000000
0!
0-
#135000000
1!
0'
1-
03
b000X000X ;
0D
b00X00000 I
b00X00000 Y
b00X00000 j
#140000000
0!
0-
#145000000
1!
b00000100 #
b00000000 $
1'
1-
b00000100 /
b00000000 0
13
b00000100 A
1D
#150000000
0!
0-
#155000000
1!
b000X0000 $
1-
b000X0000 0
b00000101 9
#160000000
0!
0-
#165000000
1!
0'
1-
03
b000X0000 ;
0D
b000X000X I
b000X000X Y
b000X000X j
#170000000
0!
0-
#175000000
1!
b00000101 #
b00000000 $
1'
1-
b00000101 /
b00000000 0
13
b00000101 A
1D
#180000000
0!
0-
#185000000
1!
b000X000X $
1-
b000X000X 0
b00000110 9
#190000000
0!
0-
#195000000
1!
0'
1-
03
b000X000X ;
0D
b000X0000 I
b000X0000 Y
b000X0000 j
#200000000
0!
0-
#205000000
1!
b00000110 #
b00000000 $
1'
1-
b00000110 /
b00000000 0
13
b00000110 A
1D
#210000000
0!
0-
#215000000
1!
b000000X0 $
1-
b000000X0 0
b00000111 9
#220000000
0!
0-
#225000000
1!
0'
1-
03
b000000X0 ;
0D
b000X000X I
b000X000X Y
b000X000X j
#230000000
0!
0-
#235000000
1!
b00000111 #
b00000000 $
1'
1-
b00000111 /
b00000000 0
13
b00000111 A
1D
#240000000
0!
0-
#245000000
1!
b00X00000 $
1-
b00X00000 0
b00001000 9
#250000000
0!
0-
#255000000
1!
0'
1-
03
b00X00000 ;
0D
b000000X0 I
b000000X0 Y
b000000X0 j
#260000000
0!
0-
#265000000
1!
b00001000 #
b00000000 $
1'
1-
b00001000 /
b00000000 0
13
b00001000 A
1D
#270000000
0!
0-
#275000000
1!
bXXXX0000 $
1-
bXXXX0000 0
b00001001 9
#280000000
0!
0-
#285000000
1!
0'
1-
03
bXXXX0000 ;
0D
b00X00000 I
b00X00000 Y
b00X00000 j
#290000000
0!
0-
#295000000
1!
b00001001 #
b00000000 $
1'
1-
b00001001 /
b00000000 0
13
b00001001 A
1D
#300000000
0!
0-
#305000000
1!
1-
b00001010 9
#310000000
0!
0-
#315000000
1!
0'
1-
03
b00000000 ;
0D
bXXXX0000 I
bXXXX0000 Y
bXXXX0000 j
#320000000
0!
0-
#325000000
1!
b00001010 #
1'
1-
b00001010 /
13
b00001010 A
1D
#330000000
0!
0-
#335000000
1!
1-
b00001011 9
#340000000
0!
0-
#345000000
1!
0'
1-
03
0D
b00000000 I
b00000000 Y
b00000000 j
#350000000
0!
0-
#355000000
1!
b00001011 #
1'
1-
b00001011 /
13
b00001011 A
1D
#360000000
0!
0-
#365000000
1!
1-
b00001100 9
#370000000
0!
0-
#375000000
1!
0'
1-
03
0D
#380000000
0!
0-
#385000000
1!
b00001100 #
1'
1-
b00001100 /
13
b00001100 A
1D
#390000000
0!
0-
#395000000
1!
1-
b00001101 9
#400000000
0!
0-
#405000000
1!
0'
1-
03
0D
#410000000
0!
0-
#415000000
1!
b00001101 #
1'
1-
b00001101 /
13
b00001101 A
1D
#420000000
0!
0-
#425000000
1!
1-
b00001110 9
#430000000
0!
0-
#435000000
1!
0'
1-
03
0D
#440000000
0!
0-
#445000000
1!
b00001110 #
1'
1-
b00001110 /
13
b00001110 A
1D
#450000000
0!
0-
#455000000
1!
1-
b00001111 9
#460000000
0!
0-
#465000000
1!
0'
1-
03
0D
#470000000
0!
0-
#475000000
1!
b00001111 #
1'
1-
b00001111 /
13
b00001111 A
1D
#480000000
0!
0-
#485000000
1!
1-
b00010000 9
#490000000
0!
0-
#495000000
1!
0'
1-
03
0D
#500000000
0!
0-
#505000000
1!
b00010000 #
1'
1-
b00010000 /
13
b00010000 A
1D
#510000000
0!
0-
#515000000
1!
b00000X0X $
1-
b00000X0X 0
b00010001 9
#520000000
0!
0-
#525000000
1!
0'
1-
03
b00000X0X ;
0D
#530000000
0!
0-
#535000000
1!
b00010001 #
b00000000 $
1'
1-
b00010001 /
b00000000 0
13
b00010001 A
1D
#540000000
0!
1,
0-
18
#545000000
1!
b000000XX $
1-
b000000XX 0
b00010010 9
#550000000
0!
0-
#555000000
1!
0'
1-
03
b000000XX ;
0D
b00000X0X I
b00000X0X Y
b00000X0X j
#560000000
0!
0,
0-
08
#565000000
1!
b00010010 #
b00000000 $
1'
1-
b00010010 /
b00000000 0
13
b00010010 A
1D
#570000000
0!
0-
#575000000
1!
1-
b00010011 9
#580000000
0!
0-
#585000000
1!
0'
1-
03
b00000000 ;
0D
b000000XX I
b000000XX Y
b000000XX j
#590000000
0!
0-
#595000000
1!
b00010011 #
1'
1-
b00010011 /
13
b00010011 A
1D
#600000000
0!
0-
#605000000
1!
1-
b00010100 9
#610000000
0!
0-
#615000000
1!
0'
1-
03
0D
b00000000 I
b00000000 Y
b00000000 j
#620000000
0!
0-
#625000000
1!
b00010100 #
1'
1-
b00010100 /
13
b00010100 A
1D
#630000000
0!
0-
#635000000
1!
1-
b00010101 9
#640000000
0!
0-
#645000000
1!
0'
1-
03
0D
#650000000
0!
0-
#655000000
1!
b00010101 #
1'
1-
b00010101 /
13
b00010101 A
1D
#660000000
0!
0-
#665000000
1!
1-
b00010110 9
#670000000
0!
0-
#675000000
1!
0'
1-
03
0D
#680000000
0!
0-
#685000000
1!
b00010110 #
1'
1-
b00010110 /
13
b00010110 A
1D
#690000000
0!
0-
#695000000
1!
1-
b00010111 9
#700000000
0!
0-
#705000000
1!
0'
1-
03
0D
#710000000
0!
0-
#715000000
1!
b00010111 #
1'
1-
b00010111 /
13
b00010111 A
1D
#720000000
0!
0-
#725000000
1!
1-
b00011000 9
#730000000
0!
0-
#735000000
1!
0'
1-
03
0D
#740000000
0!
0-
#745000000
1!
b00011000 #
1'
1-
b00011000 /
13
b00011000 A
1D
#750000000
0!
0-
#755000000
1!
1-
b00011001 9
#760000000
0!
0-
#765000000
1!
0'
1-
03
0D
#770000000
0!
0-
#775000000
1!
b00011001 #
1'
1-
b00011001 /
13
b00011001 A
1D
#780000000
0!
0-
#785000000
1!
1-
b00011010 9
#790000000
0!
0-
#795000000
1!
0'
1-
03
0D
#800000000
0!
0-
#805000000
1!
b00011010 #
1'
1-
b00011010 /
13
b00011010 A
1D
#810000000
0!
0-
#815000000
1!
1-
b00011011 9
#820000000
0!
0-
#825000000
1!
0'
1-
03
0D
#830000000
0!
0-
#835000000
1!
b00011011 #
1'
1-
b00011011 /
13
b00011011 A
1D
#840000000
0!
0-
#845000000
1!
1-
b00011100 9
#850000000
0!
0-
#855000000
1!
0'
1-
03
0D
#860000000
0!
0-
#865000000
1!
b00011100 #
1'
1-
b00011100 /
13
b00011100 A
1D
#870000000
0!
0-
#875000000
1!
1-
b00011101 9
#880000000
0!
0-
#885000000
1!
0'
1-
03
0D
#890000000
0!
0-
#895000000
1!
b00011101 #
1'
1-
b00011101 /
13
b00011101 A
1D
#900000000
0!
0-
#905000000
1!
1-
b00011110 9
#910000000
0!
0-
#915000000
1!
0'
1-
03
0D
#920000000
0!
0-
#925000000
1!
b00011110 #
1'
1-
b00011110 /
13
b00011110 A
1D
#930000000
0!
0-
#935000000
1!
1-
b00011111 9
#940000000
0!
0-
#945000000
1!
0'
1-
03
0D
#950000000
0!
0-
#955000000
1!
b00011111 #
1'
1-
b00011111 /
13
b00011111 A
1D
#960000000
0!
0-
#965000000
1!
1-
b00100000 9
#970000000
0!
0-
#975000000
1!
0'
1-
03
0D
#980000000
0!
0-
#985000000
1!
b00100000 #
1'
1-
b00100000 /
13
b00100000 A
1D
#990000000
0!
0-
#995000000
1!
1-
b00100001 9
